setup.cfg
setup.py
AreaCalculationSergey/__init__.py
AreaCalculationSergey/area.py
AreaCalculationSergey.egg-info/PKG-INFO
AreaCalculationSergey.egg-info/SOURCES.txt
AreaCalculationSergey.egg-info/dependency_links.txt
AreaCalculationSergey.egg-info/not-zip-safe
AreaCalculationSergey.egg-info/top_level.txt