Metadata-Version: 2.1
Name: AreaCalculationSergey
Version: 1.2
Summary: Area calculation of diferent figures.
Author-email: worldad20@gmail.com
